[{"t": 1782889200000, "o": "95.49", "h": "95.49", "l": "95.49", "c": "95.49", "v": "0", "vc": "0"}, {"t": 1782889500000, "o": "95.49", "h": "95.49", "l": "95.49", "c": "95.49", "v": "0", "vc": "0"}, {"t": 1782889800000, "o": "95.49", "h": "95.49", "l": "95.49", "c": "95.49", "v": "0", "vc": "0"}, {"t": 1782890100000, "o": "95.49", "h": "95.49", "l": "95.49", "c": "95.49", "v": "0", "vc": "0"}, {"t": 1782890400000, "o": "95.49", "h": "95.49", "l": "95.49", "c": "95.49", "v": "0", "vc": "0"}, {"t": 1782890700000, "o": "95.49", "h": "95.49", "l": "95.49", "c": "95.49", "v": "0", "vc": "0"}, {"t": 1782891000000, "o": "95.49", "h": "95.49", "l": "95.49", "c": "95.49", "v": "0", "vc": "0"}, {"t": 1782891300000, "o": "95.49", "h": "95.49", "l": "95.49", "c": "95.49", "v": "0", "vc": "0"}, {"t": 1782891600000, "o": "96.1", "h": "96.2", "l": "96.1", "c": "96.2", "v": "0.89", "vc": "85.599"}, {"t": 1782891900000, "o": "96.3", "h": "96.3", "l": "96.3", "c": "96.3", "v": "0.76", "vc": "73.188"}, {"t": 1782892200000, "o": "96.3", "h": "96.3", "l": "96.3", "c": "96.3", "v": "0", "vc": "0"}, {"t": 1782892500000, "o": "96.3", "h": "96.3", "l": "96.3", "c": "96.3", "v": "0", "vc": "0"}, {"t": 1782892800000, "o": "96.3", "h": "96.3", "l": "96.3", "c": "96.3", "v": "0", "vc": "0"}, {"t": 1782893100000, "o": "96.43", "h": "96.43", "l": "96.43", "c": "96.43", "v": "1.663102", "vc": "160.37292586"}, {"t": 1782893400000, "o": "96.4", "h": "96.4", "l": "96.4", "c": "96.4", "v": "0.76", "vc": "73.264"}, {"t": 1782893700000, "o": "96.2", "h": "96.2", "l": "96.2", "c": "96.2", "v": "0.83", "vc": "79.846"}, {"t": 1782894000000, "o": "96.2", "h": "96.2", "l": "96.2", "c": "96.2", "v": "0", "vc": "0"}, {"t": 1782894300000, "o": "96.2", "h": "96.2", "l": "96.2", "c": "96.2", "v": "0", "vc": "0"}, {"t": 1782894600000, "o": "96.2", "h": "96.2", "l": "96.2", "c": "96.2", "v": "0", "vc": "0"}, {"t": 1782894900000, "o": "96.2", "h": "96.2", "l": "96.2", "c": "96.2", "v": "0", "vc": "0"}, {"t": 1782895200000, "o": "96.2", "h": "96.2", "l": "96.2", "c": "96.2", "v": "0", "vc": "0"}, {"t": 1782895500000, "o": "96.2", "h": "96.2", "l": "96.2", "c": "96.2", "v": "0", "vc": "0"}, {"t": 1782895800000, "o": "96.2", "h": "96.2", "l": "96.2", "c": "96.2", "v": "0", "vc": "0"}, {"t": 1782896100000, "o": "96.88", "h": "97", "l": "96.88", "c": "97", "v": "0.207985", "vc": "20.15577232"}, {"t": 1782896400000, "o": "97", "h": "97", "l": "97", "c": "97", "v": "0", "vc": "0"}, {"t": 1782896700000, "o": "97", "h": "97", "l": "97", "c": "97", "v": "0", "vc": "0"}, {"t": 1782897000000, "o": "97", "h": "97", "l": "97", "c": "97", "v": "0", "vc": "0"}, {"t": 1782897300000, "o": "97", "h": "97", "l": "97", "c": "97", "v": "0", "vc": "0"}, {"t": 1782897600000, "o": "97", "h": "97", "l": "97", "c": "97", "v": "0", "vc": "0"}, {"t": 1782897900000, "o": "97", "h": "97", "l": "97", "c": "97", "v": "0", "vc": "0"}, {"t": 1782898200000, "o": "97", "h": "97", "l": "97", "c": "97", "v": "0", "vc": "0"}, {"t": 1782898500000, "o": "97", "h": "97", "l": "97", "c": "97", "v": "0", "vc": "0"}, {"t": 1782898800000, "o": "97", "h": "97", "l": "97", "c": "97", "v": "0", "vc": "0"}, {"t": 1782899100000, "o": "96.67", "h": "96.67", "l": "96.61", "c": "96.62", "v": "54.204519", "vc": "5237.90041049"}, {"t": 1782899400000, "o": "97", "h": "97", "l": "97", "c": "97", "v": "0.258176", "vc": "25.043072"}, {"t": 1782899700000, "o": "97", "h": "97", "l": "97", "c": "97", "v": "0", "vc": "0"}, {"t": 1782900000000, "o": "96.94", "h": "96.94", "l": "96.94", "c": "96.94", "v": "5.291945", "vc": "513.0011483"}, {"t": 1782900300000, "o": "97.05", "h": "97.1", "l": "97.05", "c": "97.1", "v": "31.583904", "vc": "3065.2368832"}, {"t": 1782900600000, "o": "97.1", "h": "97.1", "l": "97.1", "c": "97.1", "v": "0", "vc": "0"}, {"t": 1782900900000, "o": "97.1", "h": "97.1", "l": "97.1", "c": "97.1", "v": "0", "vc": "0"}, {"t": 1782901200000, "o": "97.1", "h": "97.1", "l": "97.1", "c": "97.1", "v": "0", "vc": "0"}, {"t": 1782901500000, "o": "97.1", "h": "97.1", "l": "97.1", "c": "97.1", "v": "0", "vc": "0"}, {"t": 1782901800000, "o": "97.1", "h": "97.1", "l": "97.1", "c": "97.1", "v": "0", "vc": "0"}, {"t": 1782902100000, "o": "96.62", "h": "96.62", "l": "96.62", "c": "96.62", "v": "0.051504", "vc": "4.97631648"}, {"t": 1782902400000, "o": "96.62", "h": "96.62", "l": "96.62", "c": "96.62", "v": "0", "vc": "0"}, {"t": 1782902700000, "o": "96.62", "h": "96.62", "l": "96.62", "c": "96.62", "v": "0", "vc": "0"}, {"t": 1782903000000, "o": "96.62", "h": "96.62", "l": "96.62", "c": "96.62", "v": "0", "vc": "0"}, {"t": 1782903300000, "o": "96.62", "h": "96.62", "l": "96.62", "c": "96.62", "v": "0", "vc": "0"}, {"t": 1782903600000, "o": "96.2", "h": "96.2", "l": "96.2", "c": "96.2", "v": "0.38", "vc": "36.556"}, {"t": 1782903900000, "o": "96.27", "h": "96.27", "l": "96.27", "c": "96.27", "v": "0.379829", "vc": "36.56613783"}, {"t": 1782904200000, "o": "96.39", "h": "96.39", "l": "96.39", "c": "96.39", "v": "0.258098", "vc": "24.87806622"}, {"t": 1782904500000, "o": "96.81", "h": "96.81", "l": "96.81", "c": "96.81", "v": "0.885858", "vc": "85.75991298"}, {"t": 1782904800000, "o": "96.63", "h": "96.63", "l": "96.63", "c": "96.63", "v": "1.600987", "vc": "154.70337381"}, {"t": 1782905100000, "o": "96.63", "h": "96.63", "l": "96.63", "c": "96.63", "v": "0", "vc": "0"}, {"t": 1782905400000, "o": "96.63", "h": "96.63", "l": "96.63", "c": "96.63", "v": "0", "vc": "0"}, {"t": 1782905700000, "o": "96.63", "h": "96.63", "l": "96.63", "c": "96.63", "v": "0", "vc": "0"}, {"t": 1782906000000, "o": "96.63", "h": "96.63", "l": "96.63", "c": "96.63", "v": "0", "vc": "0"}, {"t": 1782906300000, "o": "96.26", "h": "96.26", "l": "96.26", "c": "96.26", "v": "22.906832", "vc": "2205.01164832"}, {"t": 1782906600000, "o": "96.11", "h": "96.11", "l": "96.11", "c": "96.11", "v": "250", "vc": "24027.5"}, {"t": 1782906900000, "o": "96.11", "h": "96.11", "l": "96.11", "c": "96.11", "v": "0", "vc": "0"}, {"t": 1782907200000, "o": "96.11", "h": "96.11", "l": "96.11", "c": "96.11", "v": "0", "vc": "0"}, {"t": 1782907500000, "o": "96.11", "h": "96.11", "l": "96.11", "c": "96.11", "v": "0", "vc": "0"}, {"t": 1782907800000, "o": "96.21", "h": "96.21", "l": "96.21", "c": "96.21", "v": "1.600987", "vc": "154.03095927"}, {"t": 1782908100000, "o": "96.21", "h": "96.21", "l": "96.21", "c": "96.21", "v": "0", "vc": "0"}, {"t": 1782908400000, "o": "96.21", "h": "96.21", "l": "96.21", "c": "96.21", "v": "0", "vc": "0"}, {"t": 1782908700000, "o": "96.21", "h": "96.21", "l": "96.21", "c": "96.21", "v": "0", "vc": "0"}, {"t": 1782909000000, "o": "95.78", "h": "95.78", "l": "95.78", "c": "95.78", "v": "1.600987", "vc": "153.34253486"}, {"t": 1782909300000, "o": "95.78", "h": "95.78", "l": "95.78", "c": "95.78", "v": "0", "vc": "0"}, {"t": 1782909600000, "o": "95.78", "h": "95.78", "l": "95.78", "c": "95.78", "v": "0", "vc": "0"}, {"t": 1782909900000, "o": "95.78", "h": "95.78", "l": "95.78", "c": "95.78", "v": "0", "vc": "0"}, {"t": 1782910200000, "o": "95.78", "h": "95.78", "l": "95.78", "c": "95.78", "v": "0", "vc": "0"}, {"t": 1782910500000, "o": "95.78", "h": "95.78", "l": "95.78", "c": "95.78", "v": "0", "vc": "0"}, {"t": 1782910800000, "o": "96", "h": "96", "l": "96", "c": "96", "v": "0.38", "vc": "36.48"}, {"t": 1782911100000, "o": "96", "h": "96", "l": "96", "c": "96", "v": "0", "vc": "0"}, {"t": 1782911400000, "o": "96.3", "h": "96.4", "l": "96.3", "c": "96.4", "v": "0.78", "vc": "75.16"}, {"t": 1782911700000, "o": "96.4", "h": "96.4", "l": "96.4", "c": "96.4", "v": "0", "vc": "0"}, {"t": 1782912000000, "o": "96.4", "h": "96.4", "l": "96.4", "c": "96.4", "v": "0", "vc": "0"}, {"t": 1782912300000, "o": "96.4", "h": "96.4", "l": "96.4", "c": "96.4", "v": "0", "vc": "0"}, {"t": 1782912600000, "o": "96.3", "h": "96.4", "l": "96.3", "c": "96.4", "v": "0.72", "vc": "69.376"}, {"t": 1782912900000, "o": "97.1", "h": "97.1", "l": "97.1", "c": "97.1", "v": "0.19", "vc": "18.449"}, {"t": 1782913200000, "o": "97.1", "h": "97.1", "l": "97.1", "c": "97.1", "v": "0", "vc": "0"}, {"t": 1782913500000, "o": "97.15", "h": "97.25", "l": "97.15", "c": "97.25", "v": "9.758525", "vc": "948.22703295"}, {"t": 1782913800000, "o": "97.5", "h": "97.5", "l": "97.5", "c": "97.5", "v": "0.32", "vc": "31.2"}, {"t": 1782914100000, "o": "97.5", "h": "97.5", "l": "97.5", "c": "97.5", "v": "0", "vc": "0"}, {"t": 1782914400000, "o": "97.5", "h": "97.5", "l": "97.5", "c": "97.5", "v": "0", "vc": "0"}, {"t": 1782914700000, "o": "97.5", "h": "97.5", "l": "97.5", "c": "97.5", "v": "0", "vc": "0"}, {"t": 1782915000000, "o": "97.8", "h": "97.9", "l": "97.8", "c": "97.9", "v": "1.88", "vc": "183.976"}, {"t": 1782915300000, "o": "98.3", "h": "99.19", "l": "98.3", "c": "99.19", "v": "1.741773", "vc": "172.14346387"}, {"t": 1782915600000, "o": "99.19", "h": "99.19", "l": "99.19", "c": "99.19", "v": "0", "vc": "0"}, {"t": 1782915900000, "o": "99.19", "h": "99.19", "l": "99.19", "c": "99.19", "v": "0", "vc": "0"}, {"t": 1782916200000, "o": "98.8", "h": "98.8", "l": "98.5", "c": "98.5", "v": "1.85", "vc": "182.613"}, {"t": 1782916500000, "o": "98.5", "h": "98.5", "l": "98.5", "c": "98.5", "v": "0", "vc": "0"}, {"t": 1782916800000, "o": "98.5", "h": "98.5", "l": "98.5", "c": "98.5", "v": "0", "vc": "0"}, {"t": 1782917100000, "o": "98.5", "h": "98.5", "l": "98.5", "c": "98.5", "v": "0", "vc": "0"}, {"t": 1782917400000, "o": "98.5", "h": "98.5", "l": "98.5", "c": "98.5", "v": "0", "vc": "0"}, {"t": 1782917700000, "o": "98.5", "h": "98.5", "l": "98.5", "c": "98.5", "v": "0", "vc": "0"}, {"t": 1782918000000, "o": "98.5", "h": "98.5", "l": "98.5", "c": "98.5", "v": "0", "vc": "0"}, {"t": 1782918300000, "o": "98.5", "h": "98.5", "l": "98.5", "c": "98.5", "v": "0", "vc": "0"}, {"t": 1782918600000, "o": "98.5", "h": "98.5", "l": "98.5", "c": "98.5", "v": "0", "vc": "0"}, {"t": 1782918900000, "o": "98.5", "h": "98.5", "l": "98.5", "c": "98.5", "v": "0", "vc": "0"}, {"t": 1782919200000, "o": "98.5", "h": "98.5", "l": "98.5", "c": "98.5", "v": "0", "vc": "0"}, {"t": 1782919500000, "o": "99.8", "h": "99.82", "l": "99.8", "c": "99.82", "v": "1.881788", "vc": "187.82347816"}, {"t": 1782919800000, "o": "99.7", "h": "99.7", "l": "99.7", "c": "99.7", "v": "0.38", "vc": "37.886"}, {"t": 1782920100000, "o": "99.38", "h": "99.38", "l": "99.36", "c": "99.36", "v": "11.43927", "vc": "1136.7601028"}, {"t": 1782920400000, "o": "99.5", "h": "99.5", "l": "99.5", "c": "99.5", "v": "0.32", "vc": "31.84"}, {"t": 1782920700000, "o": "99.5", "h": "99.5", "l": "99.5", "c": "99.5", "v": "0", "vc": "0"}, {"t": 1782921000000, "o": "99.5", "h": "99.5", "l": "99.5", "c": "99.5", "v": "0", "vc": "0"}, {"t": 1782921300000, "o": "99.5", "h": "99.5", "l": "99.5", "c": "99.5", "v": "0", "vc": "0"}, {"t": 1782921600000, "o": "99.5", "h": "99.5", "l": "99.5", "c": "99.5", "v": "0.029849", "vc": "2.9699755"}, {"t": 1782921900000, "o": "99.5", "h": "99.5", "l": "99.5", "c": "99.5", "v": "0", "vc": "0"}, {"t": 1782922200000, "o": "99.5", "h": "99.5", "l": "99.5", "c": "99.5", "v": "0", "vc": "0"}, {"t": 1782922500000, "o": "99.5", "h": "99.5", "l": "99.5", "c": "99.5", "v": "0", "vc": "0"}, {"t": 1782922800000, "o": "99.5", "h": "99.5", "l": "99.5", "c": "99.5", "v": "0", "vc": "0"}, {"t": 1782923100000, "o": "100.35", "h": "100.35", "l": "100.35", "c": "100.35", "v": "0.437476", "vc": "43.9007166"}, {"t": 1782923400000, "o": "100.35", "h": "100.35", "l": "100.35", "c": "100.35", "v": "0", "vc": "0"}, {"t": 1782923700000, "o": "99.62", "h": "99.62", "l": "99.62", "c": "99.62", "v": "1.7784", "vc": "177.164208"}, {"t": 1782924000000, "o": "99.62", "h": "99.62", "l": "99.62", "c": "99.62", "v": "0", "vc": "0"}, {"t": 1782924300000, "o": "99.62", "h": "99.62", "l": "99.62", "c": "99.62", "v": "0", "vc": "0"}, {"t": 1782924600000, "o": "99.62", "h": "99.62", "l": "99.62", "c": "99.62", "v": "0", "vc": "0"}, {"t": 1782924900000, "o": "99.14", "h": "99.14", "l": "99.14", "c": "99.14", "v": "2.364229", "vc": "234.38966306"}, {"t": 1782925200000, "o": "99.14", "h": "99.14", "l": "99.14", "c": "99.14", "v": "0", "vc": "0"}, {"t": 1782925500000, "o": "99.1", "h": "99.1", "l": "99.1", "c": "99.1", "v": "0.32", "vc": "31.712"}, {"t": 1782925800000, "o": "99.33", "h": "99.33", "l": "99.33", "c": "99.33", "v": "1.003814", "vc": "99.70884462"}, {"t": 1782926100000, "o": "99.33", "h": "99.33", "l": "99.33", "c": "99.33", "v": "0", "vc": "0"}, {"t": 1782926400000, "o": "99.7", "h": "99.7", "l": "99.7", "c": "99.7", "v": "0.34", "vc": "33.898"}, {"t": 1782926700000, "o": "99.7", "h": "99.7", "l": "99.7", "c": "99.7", "v": "0", "vc": "0"}, {"t": 1782927000000, "o": "100", "h": "100", "l": "100", "c": "100", "v": "1.43", "vc": "143"}, {"t": 1782927300000, "o": "100", "h": "100", "l": "100", "c": "100", "v": "0", "vc": "0"}, {"t": 1782927600000, "o": "100", "h": "100", "l": "100", "c": "100", "v": "0", "vc": "0"}, {"t": 1782927900000, "o": "100", "h": "100.1", "l": "100", "c": "100.1", "v": "1.14", "vc": "114.038"}, {"t": 1782928200000, "o": "100", "h": "100", "l": "100", "c": "100", "v": "0.79", "vc": "79"}, {"t": 1782928500000, "o": "100", "h": "100", "l": "100", "c": "100", "v": "0", "vc": "0"}, {"t": 1782928800000, "o": "100.1", "h": "100.1", "l": "100.1", "c": "100.1", "v": "14.381077", "vc": "1439.5458077"}, {"t": 1782929100000, "o": "99.9", "h": "99.9", "l": "99.9", "c": "99.9", "v": "0.14493", "vc": "14.478507"}, {"t": 1782929400000, "o": "99.9", "h": "99.9", "l": "99.9", "c": "99.9", "v": "0", "vc": "0"}, {"t": 1782929700000, "o": "99.9", "h": "99.9", "l": "99.9", "c": "99.9", "v": "0", "vc": "0"}, {"t": 1782930000000, "o": "99.9", "h": "99.9", "l": "99.9", "c": "99.9", "v": "0", "vc": "0"}, {"t": 1782930300000, "o": "99.9", "h": "99.9", "l": "99.9", "c": "99.9", "v": "0", "vc": "0"}, {"t": 1782930600000, "o": "99.9", "h": "99.9", "l": "99.9", "c": "99.9", "v": "0", "vc": "0"}, {"t": 1782930900000, "o": "99.9", "h": "99.9", "l": "99.9", "c": "99.9", "v": "0", "vc": "0"}, {"t": 1782931200000, "o": "99.9", "h": "99.9", "l": "99.9", "c": "99.9", "v": "0", "vc": "0"}, {"t": 1782931500000, "o": "99.63", "h": "99.63", "l": "99.63", "c": "99.63", "v": "0.292415", "vc": "29.13330645"}, {"t": 1782931800000, "o": "99.63", "h": "99.63", "l": "99.63", "c": "99.63", "v": "0", "vc": "0"}, {"t": 1782932100000, "o": "99.63", "h": "99.63", "l": "99.63", "c": "99.63", "v": "0", "vc": "0"}, {"t": 1782932400000, "o": "99.8", "h": "99.8", "l": "99.8", "c": "99.8", "v": "0.38", "vc": "37.924"}, {"t": 1782932700000, "o": "99.8", "h": "99.8", "l": "99.8", "c": "99.8", "v": "0", "vc": "0"}, {"t": 1782933000000, "o": "99.7", "h": "99.7", "l": "99.7", "c": "99.7", "v": "0.55", "vc": "54.835"}, {"t": 1782933300000, "o": "99.7", "h": "99.7", "l": "99.7", "c": "99.7", "v": "0", "vc": "0"}, {"t": 1782933600000, "o": "99.7", "h": "99.7", "l": "99.7", "c": "99.7", "v": "0", "vc": "0"}, {"t": 1782933900000, "o": "99.37", "h": "99.37", "l": "99.37", "c": "99.37", "v": "0.02707", "vc": "2.6899459"}, {"t": 1782934200000, "o": "99.37", "h": "99.37", "l": "99.37", "c": "99.37", "v": "0", "vc": "0"}, {"t": 1782934500000, "o": "99.42", "h": "99.42", "l": "99.42", "c": "99.42", "v": "3.556496", "vc": "353.58683232"}, {"t": 1782934800000, "o": "99.42", "h": "99.42", "l": "99.42", "c": "99.42", "v": "0", "vc": "0"}, {"t": 1782935100000, "o": "99.42", "h": "99.42", "l": "99.42", "c": "99.42", "v": "0", "vc": "0"}, {"t": 1782935400000, "o": "99.42", "h": "99.42", "l": "99.42", "c": "99.42", "v": "0", "vc": "0"}, {"t": 1782935700000, "o": "99.42", "h": "99.42", "l": "99.42", "c": "99.42", "v": "0", "vc": "0"}, {"t": 1782936000000, "o": "98.9", "h": "98.9", "l": "98.9", "c": "98.9", "v": "0.38", "vc": "37.582"}, {"t": 1782936300000, "o": "98.9", "h": "98.9", "l": "98.9", "c": "98.9", "v": "0", "vc": "0"}, {"t": 1782936600000, "o": "98.73", "h": "98.73", "l": "98.73", "c": "98.73", "v": "0.027042", "vc": "2.66985666"}, {"t": 1782936900000, "o": "98.73", "h": "98.73", "l": "98.73", "c": "98.73", "v": "0", "vc": "0"}, {"t": 1782937200000, "o": "98.73", "h": "98.73", "l": "98.73", "c": "98.73", "v": "0", "vc": "0"}, {"t": 1782937500000, "o": "98.73", "h": "98.73", "l": "98.73", "c": "98.73", "v": "0", "vc": "0"}, {"t": 1782937800000, "o": "98.98", "h": "98.98", "l": "98.98", "c": "98.98", "v": "1.635355", "vc": "161.8674379"}, {"t": 1782938100000, "o": "98.95", "h": "98.95", "l": "98.95", "c": "98.95", "v": "1.526028", "vc": "151.0004706"}, {"t": 1782938400000, "o": "99.38", "h": "99.38", "l": "99.16", "c": "99.16", "v": "54.152141", "vc": "5376.08766712"}, {"t": 1782938700000, "o": "99.16", "h": "99.16", "l": "99.16", "c": "99.16", "v": "0", "vc": "0"}, {"t": 1782939000000, "o": "99.48", "h": "99.48", "l": "99.48", "c": "99.48", "v": "7.696297", "vc": "765.62762556"}, {"t": 1782939300000, "o": "99.48", "h": "99.48", "l": "99.48", "c": "99.48", "v": "0", "vc": "0"}, {"t": 1782939600000, "o": "99.76", "h": "100", "l": "99.76", "c": "100", "v": "3.986756", "vc": "397.95677856"}, {"t": 1782939900000, "o": "100", "h": "100", "l": "100", "c": "100", "v": "0", "vc": "0"}, {"t": 1782940200000, "o": "100.3", "h": "100.3", "l": "100.2", "c": "100.2", "v": "1.01", "vc": "101.278"}, {"t": 1782940500000, "o": "100.2", "h": "100.2", "l": "100.2", "c": "100.2", "v": "0", "vc": "0"}, {"t": 1782940800000, "o": "100.2", "h": "100.2", "l": "100.2", "c": "100.2", "v": "0", "vc": "0"}, {"t": 1782941100000, "o": "100.2", "h": "100.2", "l": "100.2", "c": "100.2", "v": "0", "vc": "0"}, {"t": 1782941400000, "o": "100.5", "h": "100.5", "l": "100.5", "c": "100.5", "v": "7.344414", "vc": "738.113607"}, {"t": 1782941700000, "o": "100.5", "h": "100.5", "l": "100.5", "c": "100.5", "v": "0", "vc": "0"}, {"t": 1782942000000, "o": "100.7", "h": "100.7", "l": "100.58", "c": "100.58", "v": "6.013297", "vc": "604.85821226"}, {"t": 1782942300000, "o": "100.58", "h": "100.58", "l": "100.58", "c": "100.58", "v": "0", "vc": "0"}, {"t": 1782942600000, "o": "100.92", "h": "100.92", "l": "100.92", "c": "100.92", "v": "3.575421", "vc": "360.83148732"}, {"t": 1782942900000, "o": "100.98", "h": "100.98", "l": "100.98", "c": "100.98", "v": "11.260719", "vc": "1137.10740462"}, {"t": 1782943200000, "o": "100.98", "h": "100.98", "l": "100.98", "c": "100.98", "v": "0", "vc": "0"}, {"t": 1782943500000, "o": "100.98", "h": "100.98", "l": "100.98", "c": "100.98", "v": "0", "vc": "0"}, {"t": 1782943800000, "o": "100.98", "h": "100.98", "l": "100.98", "c": "100.98", "v": "0", "vc": "0"}, {"t": 1782944100000, "o": "100.98", "h": "100.98", "l": "100.98", "c": "100.98", "v": "0", "vc": "0"}, {"t": 1782944400000, "o": "100.96", "h": "100.97", "l": "100.96", "c": "100.97", "v": "44.894772", "vc": "4532.94909327"}, {"t": 1782944700000, "o": "100.97", "h": "100.97", "l": "100.97", "c": "100.97", "v": "0", "vc": "0"}, {"t": 1782945000000, "o": "100.97", "h": "100.97", "l": "100.97", "c": "100.97", "v": "0", "vc": "0"}, {"t": 1782945300000, "o": "100.97", "h": "100.97", "l": "100.97", "c": "100.97", "v": "0", "vc": "0"}, {"t": 1782945600000, "o": "100.97", "h": "100.97", "l": "100.97", "c": "100.97", "v": "0", "vc": "0"}, {"t": 1782945900000, "o": "100.29", "h": "100.29", "l": "100.18", "c": "100.18", "v": "56.492017", "vc": "5660.64596001"}, {"t": 1782946200000, "o": "100.18", "h": "100.18", "l": "100.18", "c": "100.18", "v": "0", "vc": "0"}, {"t": 1782946500000, "o": "100.14", "h": "100.14", "l": "100.14", "c": "100.14", "v": "0.275373", "vc": "27.57585222"}, {"t": 1782946800000, "o": "100", "h": "100", "l": "99.98", "c": "99.98", "v": "25.91976", "vc": "2591.4754048"}, {"t": 1782947100000, "o": "99.81", "h": "99.97", "l": "99.81", "c": "99.97", "v": "12.057589", "vc": "1205.35760449"}, {"t": 1782947400000, "o": "99.97", "h": "99.97", "l": "99.97", "c": "99.97", "v": "0", "vc": "0"}, {"t": 1782947700000, "o": "99.97", "h": "99.97", "l": "99.97", "c": "99.97", "v": "0", "vc": "0"}, {"t": 1782948000000, "o": "99.97", "h": "99.97", "l": "99.97", "c": "99.97", "v": "5.23197", "vc": "523.0400409"}, {"t": 1782948300000, "o": "99.97", "h": "99.97", "l": "99.97", "c": "99.97", "v": "0", "vc": "0"}, {"t": 1782948600000, "o": "100", "h": "100.09", "l": "100", "c": "100.09", "v": "10.371008", "vc": "1037.99999072"}, {"t": 1782948900000, "o": "99.9", "h": "99.9", "l": "99.72", "c": "99.72", "v": "1.63891", "vc": "163.5473052"}, {"t": 1782949200000, "o": "99.72", "h": "99.72", "l": "99.72", "c": "99.72", "v": "5.257408", "vc": "524.26872576"}, {"t": 1782949500000, "o": "99.66", "h": "99.66", "l": "99.66", "c": "99.66", "v": "0.115706", "vc": "11.53125996"}, {"t": 1782949800000, "o": "99.66", "h": "99.66", "l": "99.66", "c": "99.66", "v": "0", "vc": "0"}, {"t": 1782950100000, "o": "99.66", "h": "99.66", "l": "99.66", "c": "99.66", "v": "0", "vc": "0"}, {"t": 1782950400000, "o": "99.66", "h": "99.66", "l": "99.66", "c": "99.66", "v": "0", "vc": "0"}, {"t": 1782950700000, "o": "99.66", "h": "99.66", "l": "99.66", "c": "99.66", "v": "0", "vc": "0"}, {"t": 1782951000000, "o": "99.66", "h": "99.66", "l": "99.66", "c": "99.66", "v": "0", "vc": "0"}, {"t": 1782951300000, "o": "99.66", "h": "99.66", "l": "99.66", "c": "99.66", "v": "0", "vc": "0"}, {"t": 1782951600000, "o": "99.5", "h": "99.5", "l": "99.5", "c": "99.5", "v": "0.38", "vc": "37.81"}, {"t": 1782951900000, "o": "99.5", "h": "99.5", "l": "99.5", "c": "99.5", "v": "0", "vc": "0"}, {"t": 1782952200000, "o": "99.5", "h": "99.5", "l": "99.5", "c": "99.5", "v": "0", "vc": "0"}, {"t": 1782952500000, "o": "99.5", "h": "99.5", "l": "99.5", "c": "99.5", "v": "0", "vc": "0"}, {"t": 1782952800000, "o": "99.5", "h": "99.5", "l": "99.5", "c": "99.5", "v": "0", "vc": "0"}, {"t": 1782953100000, "o": "99.5", "h": "99.5", "l": "99.5", "c": "99.5", "v": "0", "vc": "0"}, {"t": 1782953400000, "o": "99.5", "h": "99.5", "l": "99.5", "c": "99.5", "v": "0", "vc": "0"}, {"t": 1782953700000, "o": "99.5", "h": "99.5", "l": "99.5", "c": "99.5", "v": "0", "vc": "0"}, {"t": 1782954000000, "o": "99.5", "h": "99.5", "l": "99.5", "c": "99.5", "v": "0", "vc": "0"}, {"t": 1782954300000, "o": "99.5", "h": "99.5", "l": "99.5", "c": "99.5", "v": "0", "vc": "0"}, {"t": 1782954600000, "o": "99.5", "h": "99.5", "l": "99.5", "c": "99.5", "v": "0", "vc": "0"}, {"t": 1782954900000, "o": "99.5", "h": "99.5", "l": "99.5", "c": "99.5", "v": "0", "vc": "0"}, {"t": 1782955200000, "o": "99.5", "h": "99.5", "l": "99.5", "c": "99.5", "v": "0", "vc": "0"}, {"t": 1782955500000, "o": "99.5", "h": "99.5", "l": "99.5", "c": "99.5", "v": "0", "vc": "0"}, {"t": 1782955800000, "o": "100.3", "h": "100.3", "l": "100.3", "c": "100.3", "v": "0.67", "vc": "67.201"}, {"t": 1782956100000, "o": "100.3", "h": "100.3", "l": "100.3", "c": "100.3", "v": "0", "vc": "0"}, {"t": 1782956400000, "o": "100.3", "h": "100.3", "l": "100.3", "c": "100.3", "v": "0", "vc": "0"}, {"t": 1782956700000, "o": "100.3", "h": "100.3", "l": "100.3", "c": "100.3", "v": "0", "vc": "0"}, {"t": 1782957000000, "o": "100.3", "h": "100.3", "l": "100.3", "c": "100.3", "v": "0", "vc": "0"}, {"t": 1782957300000, "o": "100.3", "h": "100.3", "l": "100.3", "c": "100.3", "v": "0", "vc": "0"}, {"t": 1782957600000, "o": "100.5", "h": "100.5", "l": "100.5", "c": "100.5", "v": "6.780733", "vc": "681.4636665"}, {"t": 1782957900000, "o": "100.5", "h": "100.5", "l": "100.5", "c": "100.5", "v": "0", "vc": "0"}, {"t": 1782958200000, "o": "100.5", "h": "100.5", "l": "100.5", "c": "100.5", "v": "0", "vc": "0"}, {"t": 1782958500000, "o": "100.5", "h": "100.5", "l": "100.5", "c": "100.5", "v": "0", "vc": "0"}, {"t": 1782958800000, "o": "100.5", "h": "100.5", "l": "100.5", "c": "100.5", "v": "0", "vc": "0"}, {"t": 1782959100000, "o": "100.5", "h": "100.5", "l": "100.5", "c": "100.5", "v": "0", "vc": "0"}, {"t": 1782959400000, "o": "100.5", "h": "100.5", "l": "100.5", "c": "100.5", "v": "0", "vc": "0"}, {"t": 1782959700000, "o": "100.5", "h": "100.5", "l": "100.5", "c": "100.5", "v": "0", "vc": "0"}, {"t": 1782960000000, "o": "100.5", "h": "100.5", "l": "100.5", "c": "100.5", "v": "0", "vc": "0"}, {"t": 1782960300000, "o": "100.5", "h": "100.5", "l": "100.5", "c": "100.5", "v": "0", "vc": "0"}, {"t": 1782960600000, "o": "100.5", "h": "100.5", "l": "100.5", "c": "100.5", "v": "0", "vc": "0"}, {"t": 1782960900000, "o": "100.5", "h": "100.5", "l": "100.5", "c": "100.5", "v": "0", "vc": "0"}, {"t": 1782961200000, "o": "100.5", "h": "100.5", "l": "100.5", "c": "100.5", "v": "0", "vc": "0"}, {"t": 1782961500000, "o": "100.97", "h": "100.97", "l": "100.97", "c": "100.97", "v": "0.11", "vc": "11.1067"}, {"t": 1782961800000, "o": "100.97", "h": "100.97", "l": "100.97", "c": "100.97", "v": "0", "vc": "0"}, {"t": 1782962100000, "o": "100.97", "h": "100.97", "l": "100.97", "c": "100.97", "v": "0", "vc": "0"}, {"t": 1782962400000, "o": "100.26", "h": "100.26", "l": "100.26", "c": "100.26", "v": "4.987033", "vc": "499.99992858"}, {"t": 1782962700000, "o": "100.49", "h": "101.05", "l": "100.49", "c": "101.05", "v": "166.907263", "vc": "16772.57245887"}, {"t": 1782963000000, "o": "100.73", "h": "100.73", "l": "100.73", "c": "100.73", "v": "4.963764", "vc": "499.99994772"}, {"t": 1782963300000, "o": "100.73", "h": "100.73", "l": "100.73", "c": "100.73", "v": "0", "vc": "0"}, {"t": 1782963600000, "o": "100.73", "h": "100.73", "l": "100.73", "c": "100.73", "v": "0", "vc": "0"}, {"t": 1782963900000, "o": "100.73", "h": "100.73", "l": "100.73", "c": "100.73", "v": "0", "vc": "0"}, {"t": 1782964200000, "o": "100.73", "h": "100.73", "l": "100.73", "c": "100.73", "v": "0", "vc": "0"}, {"t": 1782964500000, "o": "100.73", "h": "100.73", "l": "100.73", "c": "100.73", "v": "0", "vc": "0"}, {"t": 1782964800000, "o": "100.73", "h": "100.73", "l": "100.73", "c": "100.73", "v": "0", "vc": "0"}, {"t": 1782965100000, "o": "100.73", "h": "100.73", "l": "100.73", "c": "100.73", "v": "0", "vc": "0"}, {"t": 1782965400000, "o": "100.73", "h": "100.73", "l": "100.73", "c": "100.73", "v": "0", "vc": "0"}, {"t": 1782965700000, "o": "100.73", "h": "100.73", "l": "100.73", "c": "100.73", "v": "0", "vc": "0"}, {"t": 1782966000000, "o": "100.73", "h": "100.73", "l": "100.73", "c": "100.73", "v": "0", "vc": "0"}, {"t": 1782966300000, "o": "100.73", "h": "100.73", "l": "100.73", "c": "100.73", "v": "0", "vc": "0"}, {"t": 1782966600000, "o": "100.73", "h": "100.73", "l": "100.73", "c": "100.73", "v": "0", "vc": "0"}, {"t": 1782966900000, "o": "100.73", "h": "100.73", "l": "100.73", "c": "100.73", "v": "0", "vc": "0"}, {"t": 1782967200000, "o": "100.73", "h": "100.73", "l": "100.73", "c": "100.73", "v": "0", "vc": "0"}, {"t": 1782967500000, "o": "100.73", "h": "100.73", "l": "100.73", "c": "100.73", "v": "0", "vc": "0"}, {"t": 1782967800000, "o": "100.8", "h": "100.87", "l": "100.8", "c": "100.87", "v": "2.119957", "vc": "213.80646259"}, {"t": 1782968100000, "o": "100.7", "h": "100.7", "l": "100.7", "c": "100.7", "v": "0.88", "vc": "88.616"}, {"t": 1782968400000, "o": "100.7", "h": "100.7", "l": "100.7", "c": "100.7", "v": "0", "vc": "0"}, {"t": 1782968700000, "o": "100.7", "h": "100.7", "l": "100.7", "c": "100.7", "v": "0", "vc": "0"}, {"t": 1782969000000, "o": "100.7", "h": "100.7", "l": "100.7", "c": "100.7", "v": "0", "vc": "0"}, {"t": 1782969300000, "o": "100.7", "h": "100.7", "l": "100.7", "c": "100.7", "v": "0", "vc": "0"}, {"t": 1782969600000, "o": "100.7", "h": "100.7", "l": "100.7", "c": "100.7", "v": "0", "vc": "0"}, {"t": 1782969900000, "o": "100.7", "h": "100.7", "l": "100.7", "c": "100.7", "v": "0", "vc": "0"}, {"t": 1782970200000, "o": "100.7", "h": "100.7", "l": "100.7", "c": "100.7", "v": "0", "vc": "0"}, {"t": 1782970500000, "o": "100.7", "h": "100.7", "l": "100.7", "c": "100.7", "v": "0", "vc": "0"}, {"t": 1782970800000, "o": "100.7", "h": "100.7", "l": "100.7", "c": "100.7", "v": "0", "vc": "0"}, {"t": 1782971100000, "o": "100.7", "h": "100.7", "l": "100.7", "c": "100.7", "v": "0", "vc": "0"}, {"t": 1782971400000, "o": "100.7", "h": "100.7", "l": "100.7", "c": "100.7", "v": "0", "vc": "0"}, {"t": 1782971700000, "o": "100.7", "h": "100.7", "l": "100.7", "c": "100.7", "v": "0", "vc": "0"}, {"t": 1782972000000, "o": "100.7", "h": "100.7", "l": "100.7", "c": "100.7", "v": "0", "vc": "0"}, {"t": 1782972300000, "o": "100.7", "h": "100.7", "l": "100.7", "c": "100.7", "v": "0", "vc": "0"}, {"t": 1782972600000, "o": "100.7", "h": "100.7", "l": "100.7", "c": "100.7", "v": "0", "vc": "0"}, {"t": 1782972900000, "o": "100.7", "h": "100.7", "l": "100.7", "c": "100.7", "v": "0", "vc": "0"}, {"t": 1782973200000, "o": "100.7", "h": "100.7", "l": "100.7", "c": "100.7", "v": "0", "vc": "0"}, {"t": 1782973500000, "o": "100.7", "h": "100.7", "l": "100.7", "c": "100.7", "v": "0", "vc": "0"}, {"t": 1782973800000, "o": "100.7", "h": "100.7", "l": "100.7", "c": "100.7", "v": "0", "vc": "0"}, {"t": 1782974100000, "o": "100.7", "h": "100.7", "l": "100.7", "c": "100.7", "v": "0", "vc": "0"}, {"t": 1782974400000, "o": "100.7", "h": "100.7", "l": "100.7", "c": "100.7", "v": "0", "vc": "0"}, {"t": 1782974700000, "o": "100.7", "h": "100.7", "l": "100.7", "c": "100.7", "v": "0", "vc": "0"}, {"t": 1782975000000, "o": "100.7", "h": "100.7", "l": "100.7", "c": "100.7", "v": "0", "vc": "0"}, {"t": 1782975300000, "o": "100.7", "h": "100.7", "l": "100.7", "c": "100.7", "v": "0", "vc": "0"}, {"t": 1782975600000, "o": "100.7", "h": "100.7", "l": "100.7", "c": "100.7", "v": "0", "vc": "0"}, {"t": 1782975900000, "o": "100.7", "h": "100.7", "l": "100.7", "c": "100.7", "v": "0", "vc": "0"}, {"t": 1782976200000, "o": "100.7", "h": "100.7", "l": "100.7", "c": "100.7", "v": "0", "vc": "0"}, {"t": 1782976500000, "o": "100.11", "h": "100.11", "l": "100.11", "c": "100.11", "v": "0.475556", "vc": "47.60791116"}, {"t": 1782976800000, "o": "100.11", "h": "100.11", "l": "100.11", "c": "100.11", "v": "0", "vc": "0"}, {"t": 1782977100000, "o": "100.11", "h": "100.11", "l": "100.11", "c": "100.11", "v": "0", "vc": "0"}, {"t": 1782977400000, "o": "100.11", "h": "100.11", "l": "100.11", "c": "100.11", "v": "0", "vc": "0"}, {"t": 1782977700000, "o": "100.11", "h": "100.11", "l": "100.11", "c": "100.11", "v": "0", "vc": "0"}, {"t": 1782978000000, "o": "100.11", "h": "100.11", "l": "100.11", "c": "100.11", "v": "0", "vc": "0"}, {"t": 1782978300000, "o": "100.11", "h": "100.11", "l": "100.11", "c": "100.11", "v": "0", "vc": "0"}, {"t": 1782978600000, "o": "100.11", "h": "100.11", "l": "100.11", "c": "100.11", "v": "0", "vc": "0"}, {"t": 1782978900000, "o": "100.11", "h": "100.11", "l": "100.11", "c": "100.11", "v": "0", "vc": "0"}]